luciditycli/__init__.py
luciditycli/example.cfg
luciditycli/luciditycli.py
luciditycli-0.1.7.dist-info/licenses/LICENSE
luciditycli-0.1.7.dist-info/WHEEL
luciditycli-0.1.7.dist-info/METADATA
luciditycli-0.1.7.dist-info/RECORD
