Metadata-Version: 2.4
Name: luciditycli
Version: 0.1.7
Summary: Simple module for aesthetic CLI interfaces
License-Expression: GPL-3.0-only
License-File: LICENSE
Requires-Python: >=3.12
